Metadata-Version: 1.1
Name: hammae
Version: 1.0.2
Summary: Python 3 compatible Pytohn 2 `hammae` Module.
Home-page: https://pypi.org/project/hammae
Author: Ham
Author-email: UNKNOWN
License: Python 2.1.1
Keywords: roman
Platform: UNKNOWN
Classifier: Development Status :: 5 - Production/Stable
Classifier: Intended Audience :: Developers
Classifier: Programming Language :: Python
Classifier: Programming Language :: Python :: 2
Classifier: Programming Language :: Python :: 2.6
Classifier: Programming Language :: Python :: 2.7
Classifier: Programming Language :: Python :: 3
Classifier: Programming Language :: Python :: Implementation :: CPython
Classifier: License :: OSI Approved :: Python Software Foundation License
Classifier: Programming Language :: Python
Classifier: Natural Language :: English
Classifier: Operating System :: OS Independent
